clg/logger.py
clg_logger-1.0.0.dist-info/LICENSE
clg_logger-1.0.0.dist-info/METADATA
clg_logger-1.0.0.dist-info/WHEEL
clg_logger-1.0.0.dist-info/top_level.txt
clg_logger-1.0.0.dist-info/RECORD
